activation.py
initializer.py
layer.py
loss.py
model.py
optimizer.py
parse_model.py
deeplearningkit-0.0.3.dist-info/METADATA
deeplearningkit-0.0.3.dist-info/WHEEL
deeplearningkit-0.0.3.dist-info/licenses/LICENCE
deeplearningkit-0.0.3.dist-info/RECORD
