Metadata-Version: 2.1
Name: deeplearningkit
Version: 0.0.3
Summary: Implementation of neural network
Project-URL: Homepage, https://github.com/dariansereno/deep_learning_kit
Project-URL: Issues, https://github.com/dariansereno/deep_learning_kit/issues
Author-email: Darian Sereno <dasereno@student.42.fr>
License-File: LICENCE
Classifier: License :: OSI Approved :: MIT License
Classifier: Operating System :: OS Independent
Classifier: Programming Language :: Python :: 3
Requires-Python: >3
